CHANGES.rst
LICENSE
MANIFEST.in
README.rst
pyproject.toml
setup.py
aiobotocore/__init__.py
aiobotocore/_endpoint_helpers.py
aiobotocore/args.py
aiobotocore/client.py
aiobotocore/config.py
aiobotocore/credentials.py
aiobotocore/endpoint.py
aiobotocore/eventstream.py
aiobotocore/handlers.py
aiobotocore/hooks.py
aiobotocore/httpsession.py
aiobotocore/paginate.py
aiobotocore/parsers.py
aiobotocore/response.py
aiobotocore/session.py
aiobotocore/signers.py
aiobotocore/utils.py
aiobotocore/waiter.py
aiobotocore_chrisglass.egg-info/PKG-INFO
aiobotocore_chrisglass.egg-info/SOURCES.txt
aiobotocore_chrisglass.egg-info/dependency_links.txt
aiobotocore_chrisglass.egg-info/requires.txt
aiobotocore_chrisglass.egg-info/top_level.txt