Metadata-Version: 2.1
Name: aiobotocore-chrisglass
Version: 1.4.1.1
Summary: Async client for aws services using botocore and aiohttp
Home-page: https://github.com/aio-libs/aiobotocore
Author: Nikolay Novik
Author-email: nickolainovik@gmail.com
License: Apache 2
Download-URL: https://pypi.python.org/pypi/aiobotocore
Platform: UNKNOWN
Classifier: Intended Audience :: Developers
Classifier: Intended Audience :: System Administrators
Classifier: Programming Language :: Python :: 3
Classifier: Programming Language :: Python :: 3.6
Classifier: Programming Language :: Python :: 3.7
Classifier: Programming Language :: Python :: 3.8
Classifier: Environment :: Web Environment
Classifier: Development Status :: 3 - Alpha
Classifier: Framework :: AsyncIO
Requires-Python: >=3.6
Provides-Extra: awscli
Provides-Extra: boto3
